gitignorant/__init__.py
gitignorant/py.typed
gitignorant-0.4.0.dist-info/METADATA
gitignorant-0.4.0.dist-info/WHEEL
gitignorant-0.4.0.dist-info/licenses/LICENSE
gitignorant-0.4.0.dist-info/RECORD
