Metadata-Version: 2.3
Name: gitignorant
Version: 0.4.0
Summary: A parser for gitignore files
Project-URL: Bug Tracker, https://github.com/valohai/gitignorant/issues
Project-URL: Homepage, https://github.com/valohai/gitignorant
Author-email: Aarni Koskela <aarni@valohai.com>
License-Expression: MIT
License-File: LICENSE
Classifier: License :: OSI Approved :: MIT License
Classifier: Operating System :: OS Independent
Classifier: Programming Language :: Python :: 3
Requires-Python: >=3.7
